sensorkit/otto/__init__.py
sensorkit_otto-0.1.0.dist-info/METADATA
sensorkit_otto-0.1.0.dist-info/WHEEL
sensorkit_otto-0.1.0.dist-info/RECORD
